domainhelper/__init__.py
domainhelper/domain_suffix.json
domainhelper/domainhelper.py
domainhelper-1.0.0.dist-info/LICENSE
domainhelper-1.0.0.dist-info/METADATA
domainhelper-1.0.0.dist-info/WHEEL
domainhelper-1.0.0.dist-info/top_level.txt
domainhelper-1.0.0.dist-info/RECORD
