Metadata-Version: 2.1
Name: domainhelper
Version: 1.0.0
Summary: verify the domain and operate it
Home-page: https://github.com/tiagn/domainhelper
Author: tiagn
Author-email: 347618578@qq.com
License: Apache License, Version 2.0
Platform: UNKNOWN
Classifier: Programming Language :: Python
Classifier: Programming Language :: Python :: Implementation :: CPython
Requires-Python: >=2.6
